pigboat/__init__.py
pigboat/_nbdev.py
pigboat/core.py
pigboat-0.0.1.dist-info/LICENSE
pigboat-0.0.1.dist-info/METADATA
pigboat-0.0.1.dist-info/WHEEL
pigboat-0.0.1.dist-info/entry_points.txt
pigboat-0.0.1.dist-info/top_level.txt
pigboat-0.0.1.dist-info/RECORD
