Metadata-Version: 2.1
Name: pigboat
Version: 0.0.1
Summary: Weak supervision lib
Home-page: https://github.com/lgvaz/pigboat/tree/master/
Author: Lucas Goulart Vazquez
Author-email: lgvaz42@gmail.com
License: Apache Software License 2.0
Keywords: weak-supervision
Platform: UNKNOWN
Classifier: Development Status :: 3 - Alpha
Classifier: Intended Audience :: Developers
Classifier: License :: OSI Approved :: Apache Software License
Classifier: Natural Language :: English
Classifier: Programming Language :: Python :: 3.6
Classifier: Programming Language :: Python :: 3.7
Classifier: Programming Language :: Python :: 3.8
Requires-Python: >=3.6
